inspector_facet/DiamondLoupeFacet.py
inspector_facet/__init__.py
inspector_facet/abi.py
inspector_facet/cli.py
inspector_facet/facets.py
inspector_facet/inspector.py
inspector_facet/test_facets.py
inspector_facet/version.py
inspector_facet/version.txt
inspector_facet/abis/DiamondCutFacetABI.json
inspector_facet/abis/DiamondLoupeFacet.json
inspector_facet/fixtures/cu-land-cuts.jsonl
inspector_facet/fixtures/cu-land-facets.json
inspector_facet-0.4.0.dist-info/LICENSE
inspector_facet-0.4.0.dist-info/METADATA
inspector_facet-0.4.0.dist-info/WHEEL
inspector_facet-0.4.0.dist-info/entry_points.txt
inspector_facet-0.4.0.dist-info/top_level.txt
inspector_facet-0.4.0.dist-info/RECORD
