Metadata-Version: 2.1
Name: inspector-facet
Version: 0.4.0
Summary: Inspector Facet - Inspection utility for EIP2535 Diamond proxies
Home-page: https://github.com/bugout-dev/inspector-facet
Author: Moonstream
Author-email: engineering@moonstream.to
License: UNKNOWN
Platform: UNKNOWN
Classifier: Development Status :: 3 - Alpha
Classifier: Programming Language :: Python
Classifier: License :: OSI Approved :: Apache Software License
Classifier: Topic :: Software Development :: Libraries
Requires-Python: >=3.6
License-File: LICENSE
Requires-Dist: eth-brownie
Requires-Dist: tqdm
Provides-Extra: dev
Requires-Dist: black ; extra == 'dev'
Provides-Extra: distribute
Requires-Dist: setuptools ; extra == 'distribute'
Requires-Dist: twine ; extra == 'distribute'
Requires-Dist: wheel ; extra == 'distribute'
